[{"nombre":"Primer domingo","comentarios":null,"fecha":"2023-04-02","irrenunciable":"0","tipo":"Domingo"},
{"nombre":"Segundo Domingo","comentarios":null,"fecha":"2023-04-09","irrenunciable":"1","tipo":"Domingo"},
{"nombre":"Tercer Domingo","comentarios":null,"fecha":"2023-04-16","irrenunciable":"0","tipo":"Domingo"},
{"nombre":"Cuarto Domingo","comentarios":null,"fecha":"2023-04-23","irrenunciable":"0","tipo":"Domingo"},
{"nombre":"Quinto Domingo","comentarios":null,"fecha":"2023-04-30","irrenunciable":"0","tipo":"Domingo"}]